.VERSION
AUTHORS.rst
CONTRIBUTING.rst
HISTORY.rst
LICENSE
MANIFEST.in
Pipfile
Pipfile.lock
README.rst
USAGE.rst
dev-requirements.txt
requirements.txt
setup.cfg
setup.py
docs/Makefile
docs/authors.rst
docs/conf.py
docs/contributing.rst
docs/history.rst
docs/index.rst
docs/installation.rst
docs/readme.rst
docs/usage.rst
tests/test_wikiseriesbrenttoolcli.py
wikiseriesbrenttoolcli/.VERSION
wikiseriesbrenttoolcli/AUTHORS.rst
wikiseriesbrenttoolcli/CONTRIBUTING.rst
wikiseriesbrenttoolcli/HISTORY.rst
wikiseriesbrenttoolcli/LICENSE
wikiseriesbrenttoolcli/Pipfile
wikiseriesbrenttoolcli/Pipfile.lock
wikiseriesbrenttoolcli/README.rst
wikiseriesbrenttoolcli/USAGE.rst
wikiseriesbrenttoolcli/__init__.py
wikiseriesbrenttoolcli/_version.py
wikiseriesbrenttoolcli/dev-requirements.txt
wikiseriesbrenttoolcli/requirements.txt
wikiseriesbrenttoolcli/wikiseriesbrenttoolcli.py
wikiseriesbrenttoolcli/wikiseriesbrenttoolcliexceptions.py
wikiseriesbrenttoolcli.egg-info/PKG-INFO
wikiseriesbrenttoolcli.egg-info/SOURCES.txt
wikiseriesbrenttoolcli.egg-info/dependency_links.txt
wikiseriesbrenttoolcli.egg-info/entry_points.txt
wikiseriesbrenttoolcli.egg-info/not-zip-safe
wikiseriesbrenttoolcli.egg-info/requires.txt
wikiseriesbrenttoolcli.egg-info/top_level.txt
wikiseriesbrenttoolcli/conf/logging.json-example