Metadata-Version: 2.1
Name: wikiseriesbrenttoolcli
Version: 0.1.0
Summary: a cli tool to use wikipedia to retrieve tv series information
Home-page: https://github.com/narvyk/wikiseriesbrenttoolcli
Author: brent de cubber
Author-email: blah@hotmail.com
License: MIT
Keywords: wikiseriesbrenttoolcli
Classifier: Development Status :: 3 - Alpha
Classifier: Intended Audience :: Developers
Classifier: License :: OSI Approved :: MIT License
Classifier: Natural Language :: English
Classifier: Programming Language :: Python :: 3.9
License-File: LICENSE
License-File: AUTHORS.rst
